cities_of_turkiye/__init__.py
cities_of_turkiye/main.py
cities_of_turkiye/veriler.py
cities_of_turkiye-1.0.0.dist-info/METADATA
cities_of_turkiye-1.0.0.dist-info/WHEEL
cities_of_turkiye-1.0.0.dist-info/top_level.txt
cities_of_turkiye-1.0.0.dist-info/RECORD
